{"produtos":[{"id":45,"designacao":"Trigo","categorias_id":4,"estado":"ACTIVO","created_at":"2019-01-21 23:03:44","updated_at":"2019-01-21 23:03:44","deleted_at":null,"categoria":{"id":4,"designacao":"Gr\u00e3os e Cereais","foto":null,"created_at":"2019-01-21 23:03:44","updated_at":"2019-01-21 23:03:44","deleted_at":null}},{"id":44,"designacao":"Pera Ma\u00e7\u00e3","categorias_id":1,"estado":"ACTIVO","created_at":"2019-01-21 23:03:44","updated_at":"2019-01-21 23:03:44","deleted_at":null,"categoria":{"id":1,"designacao":"Frutas","foto":null,"created_at":"2019-01-21 23:03:44","updated_at":"2019-01-21 23:03:44","deleted_at":null}},{"id":43,"designacao":"Batata Doce","categorias_id":2,"estado":"ACTIVO","created_at":"2019-01-21 23:03:44","updated_at":"2019-01-21 23:03:44","deleted_at":null,"categoria":{"id":2,"designacao":"Legumes","foto":null,"created_at":"2019-01-21 23:03:44","updated_at":"2019-01-21 23:03:44","deleted_at":null}},{"id":42,"designacao":"Maracuj\u00e1","categorias_id":1,"estado":"ACTIVO","created_at":"2019-01-21 23:03:44","updated_at":"2019-01-21 23:03:44","deleted_at":null,"categoria":{"id":1,"designacao":"Frutas","foto":null,"created_at":"2019-01-21 23:03:44","updated_at":"2019-01-21 23:03:44","deleted_at":null}},{"id":41,"designacao":"Castanha","categorias_id":4,"estado":"ACTIVO","created_at":"2019-01-21 23:03:44","updated_at":"2019-01-21 23:03:44","deleted_at":null,"categoria":{"id":4,"designacao":"Gr\u00e3os e Cereais","foto":null,"created_at":"2019-01-21 23:03:44","updated_at":"2019-01-21 23:03:44","deleted_at":null}},{"id":40,"designacao":"Feijao","categorias_id":4,"estado":"ACTIVO","created_at":"2019-01-21 23:03:44","updated_at":"2019-01-21 23:03:44","deleted_at":null,"categoria":{"id":4,"designacao":"Gr\u00e3os e Cereais","foto":null,"created_at":"2019-01-21 23:03:44","updated_at":"2019-01-21 23:03:44","deleted_at":null}},{"id":39,"designacao":"Manga Mac\u00e3","categorias_id":1,"estado":"ACTIVO","created_at":"2019-01-21 23:03:44","updated_at":"2019-01-21 23:03:44","deleted_at":null,"categoria":{"id":1,"designacao":"Frutas","foto":null,"created_at":"2019-01-21 23:03:44","updated_at":"2019-01-21 23:03:44","deleted_at":null}},{"id":38,"designacao":"Manga","categorias_id":1,"estado":"ACTIVO","created_at":"2019-01-21 23:03:44","updated_at":"2019-01-21 23:03:44","deleted_at":null,"categoria":{"id":1,"designacao":"Frutas","foto":null,"created_at":"2019-01-21 23:03:44","updated_at":"2019-01-21 23:03:44","deleted_at":null}},{"id":37,"designacao":"Banana","categorias_id":1,"estado":"ACTIVO","created_at":"2019-01-21 23:03:44","updated_at":"2019-01-21 23:03:44","deleted_at":null,"categoria":{"id":1,"designacao":"Frutas","foto":null,"created_at":"2019-01-21 23:03:44","updated_at":"2019-01-21 23:03:44","deleted_at":null}},{"id":36,"designacao":"Coco","categorias_id":1,"estado":"ACTIVO","created_at":"2019-01-21 23:03:44","updated_at":"2019-01-21 23:03:44","deleted_at":null,"categoria":{"id":1,"designacao":"Frutas","foto":null,"created_at":"2019-01-21 23:03:44","updated_at":"2019-01-21 23:03:44","deleted_at":null}},{"id":35,"designacao":"Quiabo","categorias_id":2,"estado":"ACTIVO","created_at":"2019-01-21 23:03:44","updated_at":"2019-01-21 23:03:44","deleted_at":null,"categoria":{"id":2,"designacao":"Legumes","foto":null,"created_at":"2019-01-21 23:03:44","updated_at":"2019-01-21 23:03:44","deleted_at":null}},{"id":34,"designacao":"Abacate","categorias_id":1,"estado":"ACTIVO","created_at":"2019-01-21 23:03:44","updated_at":"2019-01-21 23:03:44","deleted_at":null,"categoria":{"id":1,"designacao":"Frutas","foto":null,"created_at":"2019-01-21 23:03:44","updated_at":"2019-01-21 23:03:44","deleted_at":null}},{"id":33,"designacao":"Batata","categorias_id":2,"estado":"ACTIVO","created_at":"2019-01-21 23:03:44","updated_at":"2019-01-21 23:03:44","deleted_at":null,"categoria":{"id":2,"designacao":"Legumes","foto":null,"created_at":"2019-01-21 23:03:44","updated_at":"2019-01-21 23:03:44","deleted_at":null}},{"id":32,"designacao":"Goiaba","categorias_id":1,"estado":"ACTIVO","created_at":"2019-01-21 23:03:44","updated_at":"2019-01-21 23:03:44","deleted_at":null,"categoria":{"id":1,"designacao":"Frutas","foto":null,"created_at":"2019-01-21 23:03:44","updated_at":"2019-01-21 23:03:44","deleted_at":null}},{"id":31,"designacao":"Mandioca","categorias_id":2,"estado":"ACTIVO","created_at":"2019-01-21 23:03:44","updated_at":"2019-01-21 23:03:44","deleted_at":null,"categoria":{"id":2,"designacao":"Legumes","foto":null,"created_at":"2019-01-21 23:03:44","updated_at":"2019-01-21 23:03:44","deleted_at":null}},{"id":30,"designacao":"Tomate","categorias_id":2,"estado":"ACTIVO","created_at":"2019-01-21 23:03:44","updated_at":"2019-01-21 23:03:44","deleted_at":null,"categoria":{"id":2,"designacao":"Legumes","foto":null,"created_at":"2019-01-21 23:03:44","updated_at":"2019-01-21 23:03:44","deleted_at":null}},{"id":29,"designacao":"Lim\u00e3o","categorias_id":1,"estado":"ACTIVO","created_at":"2019-01-21 23:03:44","updated_at":"2019-01-21 23:03:44","deleted_at":null,"categoria":{"id":1,"designacao":"Frutas","foto":null,"created_at":"2019-01-21 23:03:44","updated_at":"2019-01-21 23:03:44","deleted_at":null}},{"id":28,"designacao":"Soja","categorias_id":4,"estado":"ACTIVO","created_at":"2019-01-21 23:03:44","updated_at":"2019-01-21 23:03:44","deleted_at":null,"categoria":{"id":4,"designacao":"Gr\u00e3os e Cereais","foto":null,"created_at":"2019-01-21 23:03:44","updated_at":"2019-01-21 23:03:44","deleted_at":null}},{"id":27,"designacao":"Cenoura","categorias_id":2,"estado":"ACTIVO","created_at":"2019-01-21 23:03:44","updated_at":"2019-01-21 23:03:44","deleted_at":null,"categoria":{"id":2,"designacao":"Legumes","foto":null,"created_at":"2019-01-21 23:03:44","updated_at":"2019-01-21 23:03:44","deleted_at":null}},{"id":26,"designacao":"Salsa","categorias_id":3,"estado":"ACTIVO","created_at":"2019-01-21 23:03:44","updated_at":"2019-01-21 23:03:44","deleted_at":null,"categoria":{"id":3,"designacao":"Verduras","foto":null,"created_at":"2019-01-21 23:03:44","updated_at":"2019-01-21 23:03:44","deleted_at":null}},{"id":25,"designacao":"Pessego","categorias_id":1,"estado":"ACTIVO","created_at":"2019-01-21 23:03:44","updated_at":"2019-01-21 23:03:44","deleted_at":null,"categoria":{"id":1,"designacao":"Frutas","foto":null,"created_at":"2019-01-21 23:03:44","updated_at":"2019-01-21 23:03:44","deleted_at":null}},{"id":24,"designacao":"Beterraba","categorias_id":2,"estado":"ACTIVO","created_at":"2019-01-21 23:03:44","updated_at":"2019-01-21 23:03:44","deleted_at":null,"categoria":{"id":2,"designacao":"Legumes","foto":null,"created_at":"2019-01-21 23:03:44","updated_at":"2019-01-21 23:03:44","deleted_at":null}},{"id":23,"designacao":"Cevada","categorias_id":4,"estado":"ACTIVO","created_at":"2019-01-21 23:03:44","updated_at":"2019-01-21 23:03:44","deleted_at":null,"categoria":{"id":4,"designacao":"Gr\u00e3os e Cereais","foto":null,"created_at":"2019-01-21 23:03:44","updated_at":"2019-01-21 23:03:44","deleted_at":null}},{"id":22,"designacao":"Arroz","categorias_id":4,"estado":"ACTIVO","created_at":"2019-01-21 23:03:44","updated_at":"2019-01-21 23:03:44","deleted_at":null,"categoria":{"id":4,"designacao":"Gr\u00e3os e Cereais","foto":null,"created_at":"2019-01-21 23:03:44","updated_at":"2019-01-21 23:03:44","deleted_at":null}},{"id":21,"designacao":"Morango","categorias_id":1,"estado":"ACTIVO","created_at":"2019-01-21 23:03:44","updated_at":"2019-01-21 23:03:44","deleted_at":null,"categoria":{"id":1,"designacao":"Frutas","foto":null,"created_at":"2019-01-21 23:03:44","updated_at":"2019-01-21 23:03:44","deleted_at":null}},{"id":20,"designacao":"Espinafre","categorias_id":3,"estado":"ACTIVO","created_at":"2019-01-21 23:03:44","updated_at":"2019-01-21 23:03:44","deleted_at":null,"categoria":{"id":3,"designacao":"Verduras","foto":null,"created_at":"2019-01-21 23:03:44","updated_at":"2019-01-21 23:03:44","deleted_at":null}},{"id":19,"designacao":"Milho","categorias_id":4,"estado":"ACTIVO","created_at":"2019-01-21 23:03:44","updated_at":"2019-01-21 23:03:44","deleted_at":null,"categoria":{"id":4,"designacao":"Gr\u00e3os e Cereais","foto":null,"created_at":"2019-01-21 23:03:44","updated_at":"2019-01-21 23:03:44","deleted_at":null}},{"id":18,"designacao":"Amanedoim","categorias_id":4,"estado":"ACTIVO","created_at":"2019-01-21 23:03:44","updated_at":"2019-01-21 23:03:44","deleted_at":null,"categoria":{"id":4,"designacao":"Gr\u00e3os e Cereais","foto":null,"created_at":"2019-01-21 23:03:44","updated_at":"2019-01-21 23:03:44","deleted_at":null}},{"id":17,"designacao":"Repolho","categorias_id":3,"estado":"ACTIVO","created_at":"2019-01-21 23:03:44","updated_at":"2019-01-21 23:03:44","deleted_at":null,"categoria":{"id":3,"designacao":"Verduras","foto":null,"created_at":"2019-01-21 23:03:44","updated_at":"2019-01-21 23:03:44","deleted_at":null}},{"id":16,"designacao":"Cebola","categorias_id":2,"estado":"ACTIVO","created_at":"2019-01-21 23:03:44","updated_at":"2019-01-21 23:03:44","deleted_at":null,"categoria":{"id":2,"designacao":"Legumes","foto":null,"created_at":"2019-01-21 23:03:44","updated_at":"2019-01-21 23:03:44","deleted_at":null}},{"id":15,"designacao":"Pipino","categorias_id":2,"estado":"ACTIVO","created_at":"2019-01-21 23:03:44","updated_at":"2019-01-21 23:03:44","deleted_at":null,"categoria":{"id":2,"designacao":"Legumes","foto":null,"created_at":"2019-01-21 23:03:44","updated_at":"2019-01-21 23:03:44","deleted_at":null}},{"id":14,"designacao":"Pimenta","categorias_id":2,"estado":"ACTIVO","created_at":"2019-01-21 23:03:44","updated_at":"2019-01-21 23:03:44","deleted_at":null,"categoria":{"id":2,"designacao":"Legumes","foto":null,"created_at":"2019-01-21 23:03:44","updated_at":"2019-01-21 23:03:44","deleted_at":null}},{"id":13,"designacao":"Br\u00f3colos","categorias_id":3,"estado":"ACTIVO","created_at":"2019-01-21 23:03:44","updated_at":"2019-01-21 23:03:44","deleted_at":null,"categoria":{"id":3,"designacao":"Verduras","foto":null,"created_at":"2019-01-21 23:03:44","updated_at":"2019-01-21 23:03:44","deleted_at":null}},{"id":12,"designacao":"Laranja","categorias_id":1,"estado":"ACTIVO","created_at":"2019-01-21 23:03:44","updated_at":"2019-01-21 23:03:44","deleted_at":null,"categoria":{"id":1,"designacao":"Frutas","foto":null,"created_at":"2019-01-21 23:03:44","updated_at":"2019-01-21 23:03:44","deleted_at":null}},{"id":11,"designacao":"Tangerina","categorias_id":1,"estado":"ACTIVO","created_at":"2019-01-21 23:03:44","updated_at":"2019-01-21 23:03:44","deleted_at":null,"categoria":{"id":1,"designacao":"Frutas","foto":null,"created_at":"2019-01-21 23:03:44","updated_at":"2019-01-21 23:03:44","deleted_at":null}},{"id":10,"designacao":"Alface","categorias_id":3,"estado":"ACTIVO","created_at":"2019-01-21 23:03:44","updated_at":"2019-01-21 23:03:44","deleted_at":null,"categoria":{"id":3,"designacao":"Verduras","foto":null,"created_at":"2019-01-21 23:03:44","updated_at":"2019-01-21 23:03:44","deleted_at":null}},{"id":9,"designacao":"Ma\u00e7\u00e3","categorias_id":1,"estado":"ACTIVO","created_at":"2019-01-21 23:03:44","updated_at":"2019-01-21 23:03:44","deleted_at":null,"categoria":{"id":1,"designacao":"Frutas","foto":null,"created_at":"2019-01-21 23:03:44","updated_at":"2019-01-21 23:03:44","deleted_at":null}},{"id":8,"designacao":"Berinjela","categorias_id":2,"estado":"ACTIVO","created_at":"2019-01-21 23:03:44","updated_at":"2019-01-21 23:03:44","deleted_at":null,"categoria":{"id":2,"designacao":"Legumes","foto":null,"created_at":"2019-01-21 23:03:44","updated_at":"2019-01-21 23:03:44","deleted_at":null}},{"id":7,"designacao":"Ervilha","categorias_id":2,"estado":"ACTIVO","created_at":"2019-01-21 23:03:44","updated_at":"2019-01-21 23:03:44","deleted_at":null,"categoria":{"id":2,"designacao":"Legumes","foto":null,"created_at":"2019-01-21 23:03:44","updated_at":"2019-01-21 23:03:44","deleted_at":null}},{"id":6,"designacao":"Figo","categorias_id":1,"estado":"ACTIVO","created_at":"2019-01-21 23:03:44","updated_at":"2019-01-21 23:03:44","deleted_at":null,"categoria":{"id":1,"designacao":"Frutas","foto":null,"created_at":"2019-01-21 23:03:44","updated_at":"2019-01-21 23:03:44","deleted_at":null}},{"id":5,"designacao":"Abobora Seca","categorias_id":2,"estado":"ACTIVO","created_at":"2019-01-21 23:03:44","updated_at":"2019-01-21 23:03:44","deleted_at":null,"categoria":{"id":2,"designacao":"Legumes","foto":null,"created_at":"2019-01-21 23:03:44","updated_at":"2019-01-21 23:03:44","deleted_at":null}},{"id":4,"designacao":"Alho","categorias_id":4,"estado":"ACTIVO","created_at":"2019-01-21 23:03:44","updated_at":"2019-01-21 23:03:44","deleted_at":null,"categoria":{"id":4,"designacao":"Gr\u00e3os e Cereais","foto":null,"created_at":"2019-01-21 23:03:44","updated_at":"2019-01-21 23:03:44","deleted_at":null}},{"id":3,"designacao":"Uva","categorias_id":1,"estado":"ACTIVO","created_at":"2019-01-21 23:03:44","updated_at":"2019-01-21 23:03:44","deleted_at":null,"categoria":{"id":1,"designacao":"Frutas","foto":null,"created_at":"2019-01-21 23:03:44","updated_at":"2019-01-21 23:03:44","deleted_at":null}},{"id":2,"designacao":"Couve","categorias_id":3,"estado":"ACTIVO","created_at":"2019-01-21 23:03:44","updated_at":"2019-01-21 23:03:44","deleted_at":null,"categoria":{"id":3,"designacao":"Verduras","foto":null,"created_at":"2019-01-21 23:03:44","updated_at":"2019-01-21 23:03:44","deleted_at":null}},{"id":1,"designacao":"Anan\u00e1s","categorias_id":1,"estado":"ACTIVO","created_at":"2019-01-21 23:03:44","updated_at":"2019-01-21 23:03:44","deleted_at":null,"categoria":{"id":1,"designacao":"Frutas","foto":null,"created_at":"2019-01-21 23:03:44","updated_at":"2019-01-21 23:03:44","deleted_at":null}}],"status":200}